csco_tc123/__init__.py
csco_tc123/my_tc123.py
csco_tc123-3.1.0.dist-info/METADATA
csco_tc123-3.1.0.dist-info/WHEEL
csco_tc123-3.1.0.dist-info/top_level.txt
csco_tc123-3.1.0.dist-info/RECORD
